entropy_labs/__init__.py
entropy_labs/api/__init__.py
entropy_labs/api/inspect_helpers.py
entropy_labs/api/sentinel_api_client_helper.py
entropy_labs/logging/__init__.py
entropy_labs/mocking/__init__.py
entropy_labs/mocking/policies.py
entropy_labs/sentinel_api_client/sentinel_api_client/__init__.py
entropy_labs/sentinel_api_client/sentinel_api_client/client.py
entropy_labs/sentinel_api_client/sentinel_api_client/errors.py
entropy_labs/sentinel_api_client/sentinel_api_client/py.typed
entropy_labs/sentinel_api_client/sentinel_api_client/types.py
entropy_labs/sentinel_api_client/sentinel_api_client/api/__init__.py
entropy_labs/sentinel_api_client/sentinel_api_client/api/api/__init__.py
entropy_labs/sentinel_api_client/sentinel_api_client/api/api/get_open_api.py
entropy_labs/sentinel_api_client/sentinel_api_client/api/api/get_swagger_docs.py
entropy_labs/sentinel_api_client/sentinel_api_client/api/project/__init__.py
entropy_labs/sentinel_api_client/sentinel_api_client/api/project/create_project.py
entropy_labs/sentinel_api_client/sentinel_api_client/api/project/get_project.py
entropy_labs/sentinel_api_client/sentinel_api_client/api/project/get_projects.py
entropy_labs/sentinel_api_client/sentinel_api_client/api/request_group/__init__.py
entropy_labs/sentinel_api_client/sentinel_api_client/api/request_group/create_tool_request.py
entropy_labs/sentinel_api_client/sentinel_api_client/api/request_group/create_tool_request_group.py
entropy_labs/sentinel_api_client/sentinel_api_client/api/request_group/get_request_group.py
entropy_labs/sentinel_api_client/sentinel_api_client/api/request_group/get_request_group_status.py
entropy_labs/sentinel_api_client/sentinel_api_client/api/request_group/get_run_request_groups.py
entropy_labs/sentinel_api_client/sentinel_api_client/api/run/__init__.py
entropy_labs/sentinel_api_client/sentinel_api_client/api/run/create_run.py
entropy_labs/sentinel_api_client/sentinel_api_client/api/run/get_run.py
entropy_labs-0.1.16.dist-info/LICENSE
entropy_labs-0.1.16.dist-info/METADATA
entropy_labs-0.1.16.dist-info/WHEEL
entropy_labs-0.1.16.dist-info/entry_points.txt
entropy_labs-0.1.16.dist-info/top_level.txt
entropy_labs-0.1.16.dist-info/RECORD
