Metadata-Version: 2.1
Name: entropy_labs
Version: 0.1.16
Summary: Entropy Labs' Sentinel is an agent control plane that enables efficient oversight of thousands of parallel-running agents.
Author-email: Entropy Labs <devs@entropy-labs.ai>
License: MIT
Project-URL: Homepage, https://github.com/EntropyLabsAI/sentinel
Project-URL: Repository, https://github.com/EntropyLabsAI/sentinel.git
Classifier: Programming Language :: Python :: 3
Classifier: License :: OSI Approved :: MIT License
Classifier: Operating System :: OS Independent
Requires-Python: >=3.7
License-File: LICENSE
Requires-Dist: inspect-ai>=0.3.41
Requires-Dist: requests
Requires-Dist: openai
